{
  "type": "minecraft:brewing",
  "input": {
    "item": "minecraft:lingering_potion",
    "potion_contents": {
      "potions": "minecraft:long_strength"
    }
  },
  "reagent": {
    "item": "#overbrew:brewing/modifier/no_particles"
  },
  "output": {
    "id": "minecraft:lingering_potion",
    "components": {
      "minecraft:custom_name": {
        "translate": "item.minecraft.lingering_potion.effect.strength",
        "fallback": "Lingering Potion of Strength",
        "italic": false
      },
      "minecraft:potion_contents": {
        "custom_color": 16762624,
        "custom_effects": [
          {
            "id": "minecraft:strength",
            "amplifier": 0,
            "duration": 9600,
            "ambient": false,
            "show_particles": false,
            "show_icon": true
          }
        ]
      },
      "minecraft:lore": [
        {
          "translate": "overbrew.lore.no_particles",
          "fallback": "No Particles",
          "italic": false,
          "color": "#FC7812"
        }
      ]
    }
  }
}
