{
  "type": "minecraft:brewing",
  "input": {
    "item": "minecraft:potion",
    "potion_contents": {
      "potions": "minecraft:weakness"
    }
  },
  "reagent": {
    "item": "#overbrew:brewing/modifier/strong"
  },
  "output": {
    "id": "minecraft:potion",
    "components": {
      "minecraft:custom_name": {
        "translate": "item.minecraft.potion.effect.weakness",
        "fallback": "Potion of Weakness",
        "italic": false
      },
      "minecraft:potion_contents": {
        "custom_color": 4738376,
        "custom_effects": [
          {
            "id": "minecraft:weakness",
            "amplifier": 1,
            "duration": 900,
            "ambient": false,
            "show_particles": true,
            "show_icon": true
          }
        ]
      }
    }
  }
}
